{
  "type": "Feature",
  "properties": {
    "iso:country":"AW",
    "name:arg_x_preferred":[
        "Cuman\u00e1"
    ],
    "name:bel_x_preferred":[
        "\u0413\u043e\u0440\u0430\u0434 \u041a\u0443\u043c\u0430\u043d\u0430"
    ],
    "name:bre_x_preferred":[
        "Cuman\u00e1"
    ],
    "name:bul_x_preferred":[
        "\u041a\u0443\u043c\u0430\u043d\u0430"
    ],
    "name:cat_x_preferred":[
        "Cuman\u00e1"
    ],
    "name:deu_x_preferred":[
        "Cuman\u00e1"
    ],
    "name:epo_x_preferred":[
        "Cuman\u00e1"
    ],
    "name:eus_x_preferred":[
        "Cuman\u00e1"
    ],
    "name:fin_x_preferred":[
        "Cuman\u00e1"
    ],
    "name:spa_x_preferred":[
        "Cuman\u00e1"
    ],
    "qs:gn_country":"AW",
    "qs:gn_fcode":"PPLX",
    "qs:gn_pop":0,
    "qs:name":"Cuman\u00e1",
    "qs:name_adm0":"Aruba",
    "qs:photos":271,
    "qs:photos_1k":55,
    "qs:photos_9k":1,
    "qs:photos_9r":4,
    "qs:photos_all":271,
    "qs:photos_sr":5,
    "qs:placetype":"Suburb",
    "qs:pop_sr":"0",
    "qs:woe_adm0":23424736,
    "wof:name":"Cuman\u00e1",
    "wof:placetype":"neighbourhood"
},
  "geometry": {"coordinates":[-70.01667,12.51667],"type":"Point"}
}