{
  "type": "Feature",
  "properties": {
    "iso:country":"AW",
    "name:arg_x_preferred":[
        "Cuman\u00e1"
    ],
    "name:bel_x_preferred":[
        "\u0413\u043e\u0440\u0430\u0434 \u041a\u0443\u043c\u0430\u043d\u0430"
    ],
    "name:bel_x_variant":[
        "\u041a\u0443\u043c\u0430\u043d\u0430"
    ],
    "name:bre_x_preferred":[
        "Cuman\u00e1"
    ],
    "name:bul_x_preferred":[
        "\u041a\u0443\u043c\u0430\u043d\u0430"
    ],
    "name:cat_x_preferred":[
        "Cuman\u00e1"
    ],
    "name:ces_x_preferred":[
        "Cuman\u00e1"
    ],
    "name:deu_x_preferred":[
        "Cuman\u00e1"
    ],
    "name:epo_x_preferred":[
        "Cuman\u00e1"
    ],
    "name:eus_x_preferred":[
        "Cuman\u00e1"
    ],
    "name:fas_x_preferred":[
        "\u06a9\u0648\u0645\u0627\u0646\u0627"
    ],
    "name:fin_x_preferred":[
        "Cuman\u00e1"
    ],
    "name:fra_x_preferred":[
        "Cuman\u00e1"
    ],
    "name:glg_x_preferred":[
        "Cuman\u00e1"
    ],
    "name:hye_x_preferred":[
        "\u053f\u0578\u0582\u0574\u0561\u0576\u0561"
    ],
    "name:ind_x_preferred":[
        "Cumana"
    ],
    "name:ita_x_preferred":[
        "Cuman\u00e1"
    ],
    "name:jpn_x_preferred":[
        "\u30af\u30de\u30ca"
    ],
    "name:kat_x_preferred":[
        "\u10d9\u10e3\u10db\u10d0\u10dc\u10d0"
    ],
    "name:kor_x_preferred":[
        "\ucfe0\ub9c8\ub098"
    ],
    "name:lit_x_preferred":[
        "Kumana"
    ],
    "name:nld_x_preferred":[
        "Cuman\u00e1"
    ],
    "name:nor_x_preferred":[
        "Cuman\u00e1"
    ],
    "name:pol_x_preferred":[
        "Cuman\u00e1"
    ],
    "name:por_x_preferred":[
        "Cuman\u00e1"
    ],
    "name:que_x_preferred":[
        "Cuman\u00e1"
    ],
    "name:ron_x_preferred":[
        "Cuman\u00e1"
    ],
    "name:rus_x_preferred":[
        "\u041a\u0443\u043c\u0430\u043d\u0430"
    ],
    "name:spa_x_preferred":[
        "Cuman\u00e1"
    ],
    "name:swe_x_preferred":[
        "Cuman\u00e1"
    ],
    "name:szl_x_preferred":[
        "Cuman\u00e1"
    ],
    "name:tha_x_preferred":[
        "\u0e01\u0e39\u0e21\u0e32\u0e19\u0e32"
    ],
    "name:tur_x_preferred":[
        "Cuman\u00e1"
    ],
    "name:ukr_x_preferred":[
        "\u041a\u0443\u043c\u0430\u043d\u0430"
    ],
    "name:urd_x_preferred":[
        "\u06a9\u0648\u0645\u0627\u0646\u0627"
    ],
    "name:vol_x_preferred":[
        "Cuman\u00e1"
    ],
    "name:war_x_preferred":[
        "Cuman\u00e1"
    ],
    "name:zho_x_preferred":[
        "\u5eab\u99ac\u7d0d"
    ],
    "qs:gn_country":"AW",
    "qs:gn_fcode":"PPLX",
    "qs:gn_pop":0,
    "qs:name":"Cuman\u00e1",
    "qs:name_adm0":"Aruba",
    "qs:photos":271,
    "qs:photos_1k":55,
    "qs:photos_9k":1,
    "qs:photos_9r":4,
    "qs:photos_all":271,
    "qs:photos_sr":5,
    "qs:placetype":"Suburb",
    "qs:pop_sr":"0",
    "qs:woe_adm0":23424736,
    "wof:name":"Cuman\u00e1",
    "wof:placetype":"neighbourhood"
},
  "geometry": {"coordinates":[-70.01667,12.51667],"type":"Point"}
}