{
  "type": "Feature",
  "properties": {
    "gn:admin1_code":"00",
    "gn:asciiname":"Blumond",
    "gn:country_code":"AW",
    "gn:dem":47,
    "gn:feature_class":"P",
    "gn:feature_code":"PPLL",
    "gn:name":"Blumond",
    "gn:population":0,
    "gn:timezone":"America/Aruba",
    "iso:country":"AW",
    "wof:name":"Blumond",
    "wof:placetype":"locality"
},
  "geometry": {"coordinates":[-69.99861,12.5375],"type":"Point"}
}