{
  "type": "Feature",
  "properties": {
    "gn:admin1_code":"00",
    "gn:asciiname":"Sabana Blanco",
    "gn:cc2":"AW",
    "gn:country_code":"AW",
    "gn:dem":23,
    "gn:feature_class":"P",
    "gn:feature_code":"PPLL",
    "gn:name":"Sabana Blanco",
    "gn:population":0,
    "gn:timezone":"America/Aruba",
    "iso:country":"AW",
    "name:und_x_variant":[
        "Sabana Blancoe",
        "Sabana",
        "Sabana Blanco"
    ],
    "wof:name":"Sabana Blanco",
    "wof:placetype":"locality"
},
  "geometry": {"coordinates":[-70.01666999999999,12.51667],"type":"Point"}
}