{
  "type": "Feature",
  "properties": {
    "gn:admin1_code":"00",
    "gn:asciiname":"Balashi",
    "gn:country_code":"AW",
    "gn:dem":12,
    "gn:feature_class":"P",
    "gn:feature_code":"PPLL",
    "gn:name":"Balashi",
    "gn:population":0,
    "gn:timezone":"America/Aruba",
    "iso:country":"AW",
    "name:cat_x_preferred":[
        "Balashi"
    ],
    "wof:name":"Balashi",
    "wof:placetype":"locality"
},
  "geometry": {"coordinates":[-69.96666999999999,12.48333],"type":"Point"}
}