{
  "type": "Feature",
  "properties": {
    "gn:admin1_code":"00",
    "gn:asciiname":"Druif",
    "gn:country_code":"AW",
    "gn:dem":-9999,
    "gn:feature_class":"P",
    "gn:feature_code":"PPL",
    "gn:name":"Druif",
    "gn:population":0,
    "gn:timezone":"America/Aruba",
    "iso:country":"AW",
    "wof:name":"Druif",
    "wof:placetype":"locality"
},
  "geometry": {"coordinates":[-70.06667,12.53333],"type":"Point"}
}