{
  "type": "Feature",
  "properties": {
    "gn:admin1_code":"00",
    "gn:asciiname":"Macuarima",
    "gn:country_code":"AW",
    "gn:dem":43,
    "gn:feature_class":"P",
    "gn:feature_code":"PPLL",
    "gn:name":"Macuarima",
    "gn:population":0,
    "gn:timezone":"America/Aruba",
    "iso:country":"AW",
    "name:ceb_x_preferred":[
        "Macuarima"
    ],
    "name:swe_x_preferred":[
        "Macuarima"
    ],
    "name:urd_x_preferred":[
        "\u0645\u06cc\u06a9\u0648\u0627\u0631\u06cc\u0645\u0627"
    ],
    "wof:name":"Macuarima",
    "wof:placetype":"locality"
},
  "geometry": {"coordinates":[-69.97469,12.49889],"type":"Point"}
}