{
  "type": "Feature",
  "properties": {
    "iso:country":"AW",
    "qs:gn_pop":0,
    "qs:name":"Shete",
    "qs:name_adm0":"Aruba",
    "qs:photos":364,
    "qs:photos_1k":74,
    "qs:photos_9k":2,
    "qs:photos_9r":5,
    "qs:photos_all":364,
    "qs:photos_sr":6,
    "qs:placetype":"Town",
    "qs:pop_sr":"0",
    "qs:woe_adm0":23424736,
    "wof:name":"Shete",
    "wof:placetype":"locality"
},
  "geometry": {"coordinates":[-69.92286850000001,12.498001],"type":"Point"}
}