{
  "type": "Feature",
  "properties": {
    "gn:admin1_code":"00",
    "gn:asciiname":"Pos Abao",
    "gn:country_code":"AW",
    "gn:dem":14,
    "gn:feature_class":"P",
    "gn:feature_code":"PPLL",
    "gn:name":"Pos Abao",
    "gn:population":0,
    "gn:timezone":"America/Aruba",
    "iso:country":"AW",
    "wof:name":"Pos Abao",
    "wof:placetype":"locality"
},
  "geometry": {"coordinates":[-70.03333000000001,12.53333],"type":"Point"}
}